scraparazzie/package_test.py
scraparazzie/scraparazzie.py
scraparazzie/utils.py
scraparazzie-1.2.7.dist-info/LICENSE
scraparazzie-1.2.7.dist-info/METADATA
scraparazzie-1.2.7.dist-info/WHEEL
scraparazzie-1.2.7.dist-info/entry_points.txt
scraparazzie-1.2.7.dist-info/top_level.txt
scraparazzie-1.2.7.dist-info/RECORD
