Metadata-Version: 2.1
Name: scraparazzie
Version: 1.2.7
Summary: Python client for specific topic and keyword query in Google News Feed.
Home-page: https://herboratory.ai/portfolio/scraparazzie/
Author: Inger Noire
Author-email: herboratory@gmail.com
License: MIT
Keywords: google news feed python client feed
Platform: UNKNOWN
Classifier: License :: OSI Approved :: MIT License
Classifier: Programming Language :: Python :: 3
Classifier: Programming Language :: Python :: 3.7
Requires-Dist: beautifulsoup4
Requires-Dist: requests
Requires-Dist: fuzzywuzzy
Requires-Dist: lxml
